README.md
setup.py
kimstockquant/__init__.py
kimstockquant/backtest.py
kimstockquant/config.py
kimstockquant/indicators.py
kimstockquant/market.py
kimstockquant/quant.py
kimstockquant/tick.py
kimstockquant/trade.py
kimstockquant.egg-info/PKG-INFO
kimstockquant.egg-info/SOURCES.txt
kimstockquant.egg-info/dependency_links.txt
kimstockquant.egg-info/requires.txt
kimstockquant.egg-info/top_level.txt
kimstockquant/source/__init__.py
kimstockquant/source/aksharedata.py
kimstockquant/source/baostockdata.py
kimstockquant/source/sinadata.py
kimstockquant/source/tusharedata.py
kimstockquant/utils/__init__.py
kimstockquant/utils/dingtalk.py
kimstockquant/utils/logger.py
kimstockquant/utils/sendmail.py
kimstockquant/utils/storage.py
kimstockquant/utils/tools.py